tikit/__init__.py
tikit/cli.py
tikit/client.py
tikit/default_client.py
tikit/hdfs.py
tikit/hive.py
tikit/models.py
tikit/util.py
tikit/display_optimize/__init__.py
tikit/display_optimize/dataset.py
tikit/display_optimize/resource_group.py
tikit/display_optimize/training_model.py
tikit/display_optimize/training_task.py
tikit/templates/service_config.yaml
tikit/tencentcloud/__init__.py
tikit/tencentcloud/common/__init__.py
tikit/tencentcloud/common/abstract_client.py
tikit/tencentcloud/common/abstract_model.py
tikit/tencentcloud/common/common_client.py
tikit/tencentcloud/common/credential.py
tikit/tencentcloud/common/sign.py
tikit/tencentcloud/common/exception/__init__.py
tikit/tencentcloud/common/exception/tencent_cloud_sdk_exception.py
tikit/tencentcloud/common/http/__init__.py
tikit/tencentcloud/common/http/request.py
tikit/tencentcloud/common/profile/__init__.py
tikit/tencentcloud/common/profile/client_profile.py
tikit/tencentcloud/common/profile/http_profile.py
tikit/tencentcloud/emr/__init__.py
tikit/tencentcloud/emr/v20190103/__init__.py
tikit/tencentcloud/emr/v20190103/emr_client.py
tikit/tencentcloud/emr/v20190103/errorcodes.py
tikit/tencentcloud/emr/v20190103/models.py
tikit/tencentcloud/tione/__init__.py
tikit/tencentcloud/tione/v20211111/__init__.py
tikit/tencentcloud/tione/v20211111/errorcodes.py
tikit/tencentcloud/tione/v20211111/models.py
tikit/tencentcloud/tione/v20211111/tione_client.py
tikit/tencentcloud/wedata/__init__.py
tikit/tencentcloud/wedata/v20210820/__init__.py
tikit/tencentcloud/wedata/v20210820/errorcodes.py
tikit/tencentcloud/wedata/v20210820/models.py
tikit/tencentcloud/wedata/v20210820/wedata_client.py
tikit_lite-1.5.3.231109.dist-info/METADATA
tikit_lite-1.5.3.231109.dist-info/WHEEL
tikit_lite-1.5.3.231109.dist-info/entry_points.txt
tikit_lite-1.5.3.231109.dist-info/top_level.txt
tikit_lite-1.5.3.231109.dist-info/RECORD
